pre_commit_vauxoo/__init__.py
pre_commit_vauxoo/__main__.py
pre_commit_vauxoo/cli.py
pre_commit_vauxoo/git_hook_pre_commit
pre_commit_vauxoo/logging_colored.py
pre_commit_vauxoo/pre_commit_vauxoo.py
pre_commit_vauxoo/cfg/.bandit
pre_commit_vauxoo/cfg/.editorconfig
pre_commit_vauxoo/cfg/.eslintrc.json
pre_commit_vauxoo/cfg/.eslintrc_prettier.config.cjs
pre_commit_vauxoo/cfg/.flake8
pre_commit_vauxoo/cfg/.flake8-optional
pre_commit_vauxoo/cfg/.isort.cfg
pre_commit_vauxoo/cfg/.oca_hooks-autofix.cfg
pre_commit_vauxoo/cfg/.oca_hooks.cfg
pre_commit_vauxoo/cfg/.pre-commit-config-autofix.yaml
pre_commit_vauxoo/cfg/.pre-commit-config-optional.yaml
pre_commit_vauxoo/cfg/.pre-commit-config.yaml
pre_commit_vauxoo/cfg/.pylintrc
pre_commit_vauxoo/cfg/.pylintrc-experimental
pre_commit_vauxoo/cfg/.pylintrc-optional
pre_commit_vauxoo/cfg/doc8.ini
pre_commit_vauxoo/cfg/pyproject.toml
pre_commit_vauxoo/hooks/__init__.py
pre_commit_vauxoo/hooks/check_deactivate_jinja.py
pre_commit_vauxoo-8.2.21.dist-info/licenses/AUTHORS.rst
pre_commit_vauxoo-8.2.21.dist-info/licenses/LICENSE
pre_commit_vauxoo-8.2.21.dist-info/METADATA
pre_commit_vauxoo-8.2.21.dist-info/WHEEL
pre_commit_vauxoo-8.2.21.dist-info/entry_points.txt
pre_commit_vauxoo-8.2.21.dist-info/top_level.txt
pre_commit_vauxoo-8.2.21.dist-info/RECORD
