Metadata-Version: 2.4
Name: pre-commit-vauxoo
Version: 8.2.21
Summary: pre-commit script to run automatically the configuration and variables custom from Vauxoo
Home-page: https://github.com/Vauxoo/pre-commit-vauxoo
Author: Vauxoo
Author-email: info@vauxoo.com
License: LGPL-3.0-or-later
Project-URL: Documentation, https://pre-commit-vauxoo.readthedocs.io/
Project-URL: Changelog, https://pre-commit-vauxoo.readthedocs.io/en/latest/changelog.html
Project-URL: Issue Tracker, https://github.com/Vauxoo/pre-commit-vauxoo/issues
Classifier: Development Status :: 5 - Production/Stable
Classifier: Intended Audience :: Developers
Classifier: License :: OSI Approved :: GNU Lesser General Public License v3 or later (LGPLv3+)
Classifier: Operating System :: Unix
Classifier: Operating System :: POSIX
Classifier: Operating System :: Microsoft :: Windows
Classifier: Operating System :: MacOS
Classifier: Programming Language :: Python :: 3
Classifier: Programming Language :: Python :: 3.10
Classifier: Programming Language :: Python :: 3.11
Classifier: Programming Language :: Python :: 3.12
Classifier: Programming Language :: Python :: 3.13
Classifier: Programming Language :: Python :: 3.14
Classifier: Topic :: Utilities
Requires-Python: >=3.10
License-File: LICENSE
License-File: AUTHORS.rst
Requires-Dist: click<=8.1.8
Requires-Dist: pre-commit
Requires-Dist: jinja2
Requires-Dist: pgsanity
Dynamic: author
Dynamic: author-email
Dynamic: classifier
Dynamic: description
Dynamic: description-content-type
Dynamic: home-page
Dynamic: license
Dynamic: license-file
Dynamic: project-url
Dynamic: requires-dist
Dynamic: requires-python
Dynamic: summary
